asynctest/__init__.py
asynctest/_awaitable.py
asynctest/_fail_on.py
asynctest/case.py
asynctest/helpers.py
asynctest/mock.py
asynctest/selector.py
asynctest-0.12.4.dist-info/LICENSE.md
asynctest-0.12.4.dist-info/METADATA
asynctest-0.12.4.dist-info/WHEEL
asynctest-0.12.4.dist-info/top_level.txt
asynctest-0.12.4.dist-info/zip-safe
asynctest-0.12.4.dist-info/RECORD
