Metadata-Version: 2.1
Name: asynctest
Version: 0.12.4
Summary: Enhance the standard unittest package with features for testing asyncio libraries
Home-page: https://github.com/Martiusweb/asynctest/
Author: Martin Richard
Author-email: martius@martiusweb.net
License: Apache 2
Keywords: unittest,test,testing,asyncio,tulip,selectors,async,mock
Platform: UNKNOWN
Classifier: Development Status :: 3 - Alpha
Classifier: Intended Audience :: Developers
Classifier: Topic :: Software Development :: Testing
Classifier: License :: OSI Approved :: Apache Software License
Classifier: Programming Language :: Python :: 3.4
Classifier: Programming Language :: Python :: 3.5
Classifier: Programming Language :: Python :: 3.6
Classifier: Programming Language :: Python :: 3.7
Classifier: Programming Language :: Python :: Implementation :: CPython
Classifier: Programming Language :: Python :: Implementation :: PyPy
Requires-Python: >=3.4
